xpress9.cpython-38-x86_64-linux-gnu.so
xpress9.libs/libgomp-a34b3233.so.1.0.0
xpress9-0.3.7.dist-info/LICENSE
xpress9-0.3.7.dist-info/METADATA
xpress9-0.3.7.dist-info/WHEEL
xpress9-0.3.7.dist-info/top_level.txt
xpress9-0.3.7.dist-info/RECORD
