Metadata-Version: 2.1
Name: xpress9
Version: 0.3.7
Summary: Python bindings for the Xpress9 compression library
Home-page: https://github.com/Hugoberry/xpress9-python
Author: Igor Cotruta
Author-email: Igor Cotruta <hugoberry314@gmail.com>
License: MIT
Project-URL: Homepage, https://github.com/Hugoberry/xpress9-python
Project-URL: Bug Tracker, https://github.com/Hugoberry/xpress9-python/issues
Project-URL: Source Code, https://github.com/Hugoberry/xpress9-python
Keywords: compression,xpress9,microsoft
Classifier: Development Status :: 4 - Beta
Classifier: Intended Audience :: Developers
Classifier: License :: OSI Approved :: MIT License
Classifier: Programming Language :: Python :: 3.8
Classifier: Programming Language :: Python :: 3.9
Classifier: Programming Language :: Python :: 3.10
Classifier: Programming Language :: Python :: 3.11
Classifier: Programming Language :: Python :: 3.12
Classifier: Programming Language :: Python :: 3.13
Classifier: Operating System :: OS Independent
Classifier: Topic :: Software Development :: Libraries :: Python Modules
Classifier: Topic :: System :: Archiving :: Compression
Requires-Python: >=3.8
License-File: LICENSE
